beehaviourlab/__init__.py
beehaviourlab/_version.py
beehaviourlab/cli.py
beehaviourlab/config/__init__.py
beehaviourlab/config/cli.py
beehaviourlab/config/load_config.py
beehaviourlab/config/tracking_config.yaml
beehaviourlab/tracking/__init__.py
beehaviourlab/tracking/batch_process.py
beehaviourlab/tracking/custom_tracker.yaml
beehaviourlab/tracking/extract_flow_info.py
beehaviourlab/tracking/fix_ids.py
beehaviourlab/tracking/process_video.py
beehaviourlab/tracking/tracking_video_visualiser.py
beehaviourlab/tracking/yolo_predict_to_file.py
beehaviourlab/tracking/model/feeder_bee_YOLO.pt
beehaviourlab-0.1.3.dist-info/licenses/LICENSE
beehaviourlab-0.1.3.dist-info/METADATA
beehaviourlab-0.1.3.dist-info/WHEEL
beehaviourlab-0.1.3.dist-info/entry_points.txt
beehaviourlab-0.1.3.dist-info/top_level.txt
beehaviourlab-0.1.3.dist-info/RECORD
