Metadata-Version: 2.4
Name: beehaviourlab
Version: 0.1.3
Summary: BEEhaviourLab provides tools for detecting, tracking, and analysing bee behaviour from video data.
Author-email: Rachel Parkinson <rachel.parkinson@biology.ox.ac.uk>, Oliver King <oliver.king@dtc.ox.ac.uk>
License: Apache-2.0
Project-URL: Documentation, https://beehaviourlab.github.io/BEEhaviourLab/
Project-URL: Source, https://github.com/BEEhaviourLab/BEEhaviourLab
Project-URL: Issues, https://github.com/BEEhaviourLab/BEEhaviourLab/issues
Project-URL: Changelog, https://github.com/BEEhaviourLab/BEEhaviourLab/blob/main/CHANGELOG.md
Keywords: bee,behaviour,tracking,computer-vision,yolo
Classifier: Development Status :: 3 - Alpha
Classifier: Intended Audience :: Science/Research
Classifier: License :: OSI Approved :: Apache Software License
Classifier: Operating System :: OS Independent
Classifier: Programming Language :: Python :: 3
Classifier: Programming Language :: Python :: 3.10
Classifier: Programming Language :: Python :: 3.11
Classifier: Programming Language :: Python :: 3.12
Classifier: Programming Language :: Python :: 3.13
Classifier: Programming Language :: Python :: 3.14
Classifier: Topic :: Scientific/Engineering :: Image Recognition
Classifier: Topic :: Scientific/Engineering :: Artificial Intelligence
Requires-Python: >=3.10
License-File: LICENSE
Requires-Dist: ultralytics==8.3.78
Requires-Dist: polars>=0.20.0
Requires-Dist: click>=8.0.0
Requires-Dist: opencv-python>=4.5.0
Requires-Dist: numpy>=1.20.0
Requires-Dist: scipy>=1.7.0
Requires-Dist: matplotlib>=3.3.0
Requires-Dist: pyyaml>=5.4.0
Provides-Extra: docs
Requires-Dist: sphinx>=7.0.0; extra == "docs"
Requires-Dist: pydata-sphinx-theme>=0.15.0; extra == "docs"
Requires-Dist: sphinx-autodoc-typehints>=2.0.0; extra == "docs"
Requires-Dist: sphinx-copybutton>=0.5.2; extra == "docs"
Provides-Extra: test
Requires-Dist: pytest>=7.2.0; extra == "test"
Requires-Dist: pytest-cov>=5.0.0; extra == "test"
Provides-Extra: dev
Requires-Dist: sphinx>=7.0.0; extra == "dev"
Requires-Dist: pydata-sphinx-theme>=0.15.0; extra == "dev"
Requires-Dist: sphinx-autodoc-typehints>=2.0.0; extra == "dev"
Requires-Dist: sphinx-copybutton>=0.5.2; extra == "dev"
Requires-Dist: pytest>=7.2.0; extra == "dev"
Requires-Dist: pytest-cov>=5.0.0; extra == "dev"
Dynamic: license-file
